falsifier/__init__.py
falsifier/classes.py
falsifier/py.typed
falsifier/__/__init__.py
falsifier/__/imports.py
falsifier/__/nomina.py
falsifier-2.1.1.dist-info/METADATA
falsifier-2.1.1.dist-info/WHEEL
falsifier-2.1.1.dist-info/licenses/LICENSE.txt
falsifier-2.1.1.dist-info/RECORD
