Metadata-Version: 2.4
Name: falsifier
Version: 2.1.1
Summary: Production of falsey objects.
Project-URL: Homepage, https://github.com/emcd/python-falsifier
Project-URL: Documentation, https://emcd.github.io/python-falsifier
Project-URL: Download, https://pypi.org/project/falsifier/#files
Project-URL: Source Code, https://github.com/emcd/python-falsifier
Project-URL: Issue Tracker, https://github.com/emcd/python-falsifier/issues
Author-email: Eric McDonald <emcd@users.noreply.github.com>
License-Expression: Apache-2.0
License-File: LICENSE.txt
Keywords: comparison,falsey,identity,truthy
Classifier: Development Status :: 5 - Production/Stable
Classifier: Intended Audience :: Developers
Classifier: License :: OSI Approved :: Apache Software License
Classifier: Programming Language :: Python :: 3 :: Only
Classifier: Programming Language :: Python :: 3.10
Classifier: Programming Language :: Python :: 3.11
Classifier: Programming Language :: Python :: 3.12
Classifier: Programming Language :: Python :: 3.13
Classifier: Programming Language :: Python :: Implementation :: CPython
Classifier: Programming Language :: Python :: Implementation :: PyPy
Classifier: Topic :: Software Development
Requires-Python: >=3.10
Requires-Dist: classcore
Requires-Dist: dynadoc
Requires-Dist: typing-extensions
